cadecoder/__init__.py
cadecoder/ai/__init__.py
cadecoder/ai/prompts.py
cadecoder/cli/__init__.py
cadecoder/cli/app.py
cadecoder/cli/auth.py
cadecoder/cli/commands/__init__.py
cadecoder/cli/commands/auth.py
cadecoder/cli/commands/chat.py
cadecoder/cli/commands/context.py
cadecoder/cli/commands/mcp.py
cadecoder/cli/commands/model.py
cadecoder/cli/commands/thread.py
cadecoder/cli/commands/tools.py
cadecoder/core/__init__.py
cadecoder/core/config.py
cadecoder/core/constants.py
cadecoder/core/errors.py
cadecoder/core/logging.py
cadecoder/core/names.py
cadecoder/core/types.py
cadecoder/execution/__init__.py
cadecoder/execution/context_window.py
cadecoder/execution/orchestrator.py
cadecoder/execution/parallel.py
cadecoder/providers/__init__.py
cadecoder/providers/anthropic.py
cadecoder/providers/base.py
cadecoder/providers/ollama.py
cadecoder/providers/openai.py
cadecoder/storage/__init__.py
cadecoder/storage/threads.py
cadecoder/templates/login_failed.html
cadecoder/templates/login_success.html
cadecoder/templates/styles.css
cadecoder/tools/__init__.py
cadecoder/tools/local/__init__.py
cadecoder/tools/local/filesystem.py
cadecoder/tools/local/git.py
cadecoder/tools/local/search.py
cadecoder/tools/local/shell.py
cadecoder/tools/manager/__init__.py
cadecoder/tools/manager/base.py
cadecoder/tools/manager/composite.py
cadecoder/tools/manager/config.py
cadecoder/tools/manager/mcp.py
cadecoder/ui/__init__.py
cadecoder/ui/display.py
cadecoder/ui/session.py
cade_cli-0.4.0.dist-info/METADATA
cade_cli-0.4.0.dist-info/WHEEL
cade_cli-0.4.0.dist-info/entry_points.txt
cade_cli-0.4.0.dist-info/RECORD
