Metadata-Version: 2.4
Name: cade-cli
Version: 0.4.0
Summary: Cade - The CLI Agent from Arcade.dev
Project-URL: Homepage, https://arcade.dev
Project-URL: Documentation, https://docs.arcade.dev
Project-URL: Repository, https://github.com/arcadeai-labs/cade
Project-URL: Issues, https://github.com/arcadeai-labs/cade/issues
Project-URL: Changelog, https://github.com/arcadeai-labs/cade/releases
Author-email: "Arcade AI Inc." <dev@arcade.dev>
License: MIT
Keywords: agent,ai,arcade,cli,coding-assistant,llm,mcp
Classifier: Development Status :: 4 - Beta
Classifier: Environment :: Console
Classifier: Intended Audience :: Developers
Classifier: License :: OSI Approved :: MIT License
Classifier: Operating System :: OS Independent
Classifier: Programming Language :: Python :: 3
Classifier: Programming Language :: Python :: 3.11
Classifier: Programming Language :: Python :: 3.12
Classifier: Topic :: Software Development
Classifier: Topic :: Software Development :: Code Generators
Classifier: Typing :: Typed
Requires-Python: >=3.11
Requires-Dist: anthropic<1.0.0,>=0.34.0
Requires-Dist: arcade-core<5.0.0,>=4.1.0
Requires-Dist: arcade-mcp-server>=1.0.0
Requires-Dist: arcade-tdk>=2.0.0
Requires-Dist: authlib<2.0.0,>=1.6.0
Requires-Dist: httpx<1.0.0,>=0.27.0
Requires-Dist: openai<2.0.0,>=1.0.0
Requires-Dist: prompt-toolkit>=3.0.52
Requires-Dist: pydantic[email]<3.0.0,>=2.0.0
Requires-Dist: pyperclip<2.0.0,>=1.8.0
Requires-Dist: pyyaml<7.0.0,>=6.0
Requires-Dist: rich<14.0.0,>=13.0.0
Requires-Dist: tiktoken>=0.11.0
Requires-Dist: toml<1.0.0,>=0.10.0
Requires-Dist: typer>0.10.0
Requires-Dist: ulid==1.1
Provides-Extra: dev
Requires-Dist: mypy<2.0.0,>=1.10.0; extra == 'dev'
Requires-Dist: pytest-asyncio<1.0.0,>=0.24.0; extra == 'dev'
Requires-Dist: pytest-cov<5.0.0,>=4.0.0; extra == 'dev'
Requires-Dist: pytest-mock<4.0.0,>=3.11.0; extra == 'dev'
Requires-Dist: pytest<9.0.0,>=8.0.0; extra == 'dev'
Requires-Dist: ruff<1.0.0,>=0.5.0; extra == 'dev'
Provides-Extra: training
Requires-Dist: accelerate>=0.27.0; extra == 'training'
Requires-Dist: safetensors>=0.4.2; extra == 'training'
Requires-Dist: torch>=2.1.0; extra == 'training'
Requires-Dist: transformers>=4.38.0; extra == 'training'
